json_parser_python/__init__.py
json_parser_python/core.py
json_parser_python-0.1.0.dist-info/METADATA
json_parser_python-0.1.0.dist-info/WHEEL
json_parser_python-0.1.0.dist-info/entry_points.txt
json_parser_python-0.1.0.dist-info/top_level.txt
json_parser_python-0.1.0.dist-info/RECORD
