Metadata-Version: 2.4
Name: json_parser_python
Version: 0.1.0
Summary: This is a json parser in python
Author-email: benbates_dev_python <benbates2025@proton.me>
License: MIT
Requires-Python: >=3.8
Requires-Dist: json
